megamix/DPGMM.py
megamix/GMM.py
megamix/VBGMM.py
megamix/__init__.py
megamix/base.py
megamix/initializations.py
megamix/kmeans.py
megamix-0.2.dist-info/DESCRIPTION.rst
megamix-0.2.dist-info/METADATA
megamix-0.2.dist-info/RECORD
megamix-0.2.dist-info/WHEEL
megamix-0.2.dist-info/metadata.json
megamix-0.2.dist-info/top_level.txt
